prose/__init__.py
prose/admin.py
prose/apps.py
prose/fields.py
prose/migrations/0001_initial.py
prose/migrations/0002_alter_document_id.py
prose/migrations/__init__.py
prose/models.py
prose/static/prose/editor.css
prose/static/prose/editor.js
prose/templates/prose/forms/widgets/editor.html
prose/tests.py
prose/urls.py
prose/views.py
prose/widgets.py
django_prose-2.0.1.dist-info/LICENSE
django_prose-2.0.1.dist-info/WHEEL
django_prose-2.0.1.dist-info/METADATA
django_prose-2.0.1.dist-info/RECORD
