Metadata-Version: 2.1
Name: django-prose
Version: 2.0.1
Summary: Wonderful rich text-editing for Django
Home-page: https://github.com/withlogicco/django-prose
License: MIT
Author: Paris Kasidiaris
Author-email: paris@withlogic.co
Requires-Python: >=3.8,<4.0
Classifier: License :: OSI Approved :: MIT License
Classifier: Programming Language :: Python :: 3
Classifier: Programming Language :: Python :: 3.8
Classifier: Programming Language :: Python :: 3.9
Classifier: Programming Language :: Python :: 3.10
Classifier: Programming Language :: Python :: 3.11
Requires-Dist: bleach (>=4.0)
Requires-Dist: django (>=3.2)
Project-URL: Repository, https://github.com/withlogicco/django-prose
